bookshelf_producer/__init__.py
bookshelf_producer/actions.py
bookshelf_producer/cli.py
bookshelf_producer/constants.py
bookshelf_producer/notebook.py
bookshelf_producer/py.typed
bookshelf_producer/commands/__init__.py
bookshelf_producer/commands/cmd_publish.py
bookshelf_producer/commands/cmd_run.py
bookshelf_producer-0.4.0.dist-info/METADATA
bookshelf_producer-0.4.0.dist-info/WHEEL
bookshelf_producer-0.4.0.dist-info/entry_points.txt
bookshelf_producer-0.4.0.dist-info/RECORD
