Metadata-Version: 2.3
Name: bookshelf-producer
Version: 0.4.0
Summary: Publishing utilities for bookshelf books
Requires-Python: >=3.10
Requires-Dist: bookshelf>=0.4.0
Requires-Dist: click-log>=0.3.2
Requires-Dist: click>=8.0.1
Requires-Dist: ipykernel>6.0.0
Requires-Dist: jupytext>=1.14.7
Requires-Dist: papermill>=2.4.0
Requires-Dist: python-dotenv>=1.0.0
Requires-Dist: seaborn>=0.12.2
